{
  "height": 15,
  "layers": [

    {

      "data": [
        0,
        0,
        0,
        0,
        0,
        0,
        0,
        0,
        0,
        0,
        0,
        0,
        0,
        0,

        0,
        0,
        0,
        0,
        0,
        0,
        0,
        0,
        0,
        0,
        0,
        0,
        0,
        0,

        0,
        0,
        0,
        0,
        0,
        0,
        0,
        0,
        0,
        0,
        0,
        0,
        0,
        0,


        1,
        2,
        2,
        2,
        2,
        2,
        2,
        2,
        2,
        2,
        2,
        2,
        2,
        3,


        14,
        15,
        15,
        15,
        15,
        15,
        15,
        15,
        15,
        15,
        15,
        15,
        15,
        16
      ],
      "height": 15,
      "name": "World1Level1",
      "opacity": 1,
      "properties": {
        "time":  "1000"
      }
    }
  ]
}